{
  "date": "2026-02-05",
  "block": "5-3-1",
  "week": 3,
  "day": 2,
  "notes": "トップセットで高回数をこなし強度確認",
  "sessions": [
    {
      "type": "ベンチプレス（メイン）",
      "lift": "ベンチプレス",
      "sets": [
        {
          "weight": 90,
          "reps": 5,
          "rpe": 3,
          "comment": "",
          "1RM": 101,
          "e1RM": 117
        },
        {
          "weight": 100,
          "reps": 3,
          "rpe": 5,
          "comment": "",
          "1RM": 107,
          "e1RM": 120
        },
        {
          "weight": 110,
          "reps": 8,
          "rpe": 9,
          "comment": "8rep @9",
          "1RM": 132,
          "e1RM": 134
        }
      ]
    }
  ]
}